{
  "subjectContent": {
    "chapter_name": "Grammar Irregular Plural Noun",
    "meta": {
      "practice": "Let's learn how to identify nouns in a sentence.\nGo through each word and see,if it's a person, place, thing, or an emotion or idea.",
      "test": "Tap the play button to start the test , and choose the right answer."
    },
    "content": [
      {
        "word": "Children",
        "description": "1 Child → 4 Children",
        "image": "https://www.notion.so/image/https%3A%2F%2Fs3-us-west-2.amazonaws.com%2Fsecure.notion-static.com%2Fb6a452ee-14f3-4cb5-848a-9868a1e3e6eb%2FUntitled.png?table=block&id=7ef2ef65-3ace-4f1f-be45-948eccfa7b9f&spaceId=e3f3ef07-5851-41bd-9712-14462db96413&width=480&userId=e39db595-1844-42cc-aff8-1816b7db057d&cache=v2",
        "extra": "Childrens, Childs, Children"
      },
      {
        "word": "Men",
        "description": "1 Man → 4 Men",
        "image": "https://www.notion.so/image/https%3A%2F%2Fs3-us-west-2.amazonaws.com%2Fsecure.notion-static.com%2Fc66c2371-a40c-4daf-907f-f6c550f9be6e%2FUntitled.png?table=block&id=216feb05-ad32-4118-bd1e-bf584555995c&spaceId=e3f3ef07-5851-41bd-9712-14462db96413&width=380&userId=e39db595-1844-42cc-aff8-1816b7db057d&cache=v2",
        "extra": "Mans, Men, Mens"
      },
      {
        "word": "Women",
        "description": "1 Woman → 2 Women",
        "image": "https://www.notion.so/image/https%3A%2F%2Fs3-us-west-2.amazonaws.com%2Fsecure.notion-static.com%2Fe4f3992a-511a-4d82-bb4b-f83dd31229e2%2FUntitled.png?table=block&id=2473323f-4a04-4ff3-aa6c-12a47c529015&spaceId=e3f3ef07-5851-41bd-9712-14462db96413&width=240&userId=e39db595-1844-42cc-aff8-1816b7db057d&cache=v2",
        "extra": "Womans, Womens, Women"
      },
      {
        "word": "People ",
        "description": "1 Person → 3 People",
        "image": "https://www.notion.so/image/https%3A%2F%2Fs3-us-west-2.amazonaws.com%2Fsecure.notion-static.com%2Faf0e6311-183f-48a3-bfed-b1df72626f71%2FUntitled.png?table=block&id=ea21c27f-11ef-4b98-b164-42b1c27ab760&spaceId=e3f3ef07-5851-41bd-9712-14462db96413&width=290&userId=e39db595-1844-42cc-aff8-1816b7db057d&cache=v2",
        "extra": "Persons, People, Peoples"
      },
      {
        "word": "Mice",
        "description": "1 Mouse → 2 Mice",
        "image": "https://www.notion.so/image/https%3A%2F%2Fs3-us-west-2.amazonaws.com%2Fsecure.notion-static.com%2F7fa23e74-dcb3-44a7-853b-c5f591ae14d0%2FUntitled.png?table=block&id=24596e8c-cc42-4dcd-ae70-8b030ea96a09&spaceId=e3f3ef07-5851-41bd-9712-14462db96413&width=290&userId=e39db595-1844-42cc-aff8-1816b7db057d&cache=v2",
        "extra": "Mouses, Mice, Mices"
      },
      {
        "word": "Knives",
        "description": "1 Knife → 2 Knives",
        "image": "https://www.notion.so/image/https%3A%2F%2Fs3-us-west-2.amazonaws.com%2Fsecure.notion-static.com%2F743a703b-657d-4f8c-a19d-ce5090dd550b%2FUntitled.png?table=block&id=7231b3f8-8a08-4ed9-8fb1-5f66cbea01e6&spaceId=e3f3ef07-5851-41bd-9712-14462db96413&width=380&userId=e39db595-1844-42cc-aff8-1816b7db057d&cache=v2",
        "extra": "Knifes, Knife, Knives"
      },
      {
        "word": "Wolves",
        "description": "1 Wolf → 2 Wolves",
        "image": "https://www.notion.so/image/https%3A%2F%2Fs3-us-west-2.amazonaws.com%2Fsecure.notion-static.com%2F70981328-0e50-4a3e-8665-455c5ca6a637%2FUntitled.png?table=block&id=37774d6a-dd8d-47a1-973e-e590e26cce56&spaceId=e3f3ef07-5851-41bd-9712-14462db96413&width=290&userId=e39db595-1844-42cc-aff8-1816b7db057d&cache=v2",
        "extra": "Wolfes, Wolvs, Wolves"
      },
      {
        "word": "Fish",
        "description": "1 Fish → 2 Fish",
        "image": "https://www.notion.so/image/https%3A%2F%2Fs3-us-west-2.amazonaws.com%2Fsecure.notion-static.com%2F98c5387b-80af-448e-abb1-09e436dab864%2FUntitled.png?table=block&id=c74a93b5-4d5d-433a-9b71-9fc9ec500f4a&spaceId=e3f3ef07-5851-41bd-9712-14462db96413&width=290&userId=e39db595-1844-42cc-aff8-1816b7db057d&cache=v2",
        "extra": "Fishes, Fish,Fishs"
      },
      {
        "word": "Sheep",
        "description": "1 Sheep → 2 Sheep",
        "image": "https://www.notion.so/image/https%3A%2F%2Fs3-us-west-2.amazonaws.com%2Fsecure.notion-static.com%2F4178e312-155d-4d33-9a12-de71e34e420b%2FUntitled.png?table=block&id=95df0aeb-958f-4b4b-8813-1976dbd9737b&spaceId=e3f3ef07-5851-41bd-9712-14462db96413&width=290&userId=e39db595-1844-42cc-aff8-1816b7db057d&cache=v2",
        "extra": "Sheeps, Sheep,Sheepes"
      }
    ]
  }
}
